setup.py
bmi_cal/__init__.py
bmi_cal/bmi_cal.py
bmi_calculation.egg-info/PKG-INFO
bmi_calculation.egg-info/SOURCES.txt
bmi_calculation.egg-info/dependency_links.txt
bmi_calculation.egg-info/not-zip-safe
bmi_calculation.egg-info/top_level.txt