Metadata-Version: 2.1
Name: bmi_calculation
Version: 0.1
Summary: Calculation Body Mass Index
Author: sfgrahman
